mqtt_entity/__init__.py
mqtt_entity/client.py
mqtt_entity/device.py
mqtt_entity/entities.py
mqtt_entity/helpers.py
mqtt_entity/options.py
mqtt_entity/py.typed
mqtt_entity/supervisor.py
mqtt_entity/utils.py
mqtt_entity-1.0.19.dist-info/WHEEL
mqtt_entity-1.0.19.dist-info/METADATA
mqtt_entity-1.0.19.dist-info/RECORD
