Metadata-Version: 2.3
Name: mqtt-entity
Version: 1.0.19
Summary: MQTT client supporting Home Assistant MQTT entity auto-discovery
Keywords: asyncio,discovery,home-assistant,library,mqtt
Author: Johann Kellerman
Author-email: Johann Kellerman <kellerza@gmail.com>
License: MIT License
Classifier: Programming Language :: Python :: 3 :: Only
Classifier: Programming Language :: Python :: 3.12
Classifier: Programming Language :: Python :: 3.13
Classifier: Programming Language :: Python :: 3.14
Requires-Dist: aiohttp>3.12,<4
Requires-Dist: attrs>=25,<26
Requires-Dist: cattrs>=25,<26
Requires-Dist: colorlog
Requires-Dist: paho-mqtt>=2.1,<3
Requires-Dist: pyyaml>=6,<7 ; extra == 'options'
Requires-Python: >=3.12
Provides-Extra: options
